<?xml version="1.0" encoding="utf-8"?>
<ModMetaData>
  <name>Storytime ReRimmed: Frogs and Toads</name>
  <author>Isengriff</author>
  <supportedVersions><li>1.6</li></supportedVersions>
  <modDependenciesByVersion>
		<v1.6>
		</v1.6>
    </modDependenciesByVersion>
  <url>https://poobahsociety.wordpress.com/</url>
  <packageId>Jonah.StorytimeFrogs</packageId>
  <description>

    The hottest mod around for all your frog and toad based needs. No, I won't update the textures.

  </description>
</ModMetaData>
